DominantSparseEigenAD/CG.py
DominantSparseEigenAD/Lanczos.py
DominantSparseEigenAD/__init__.py
DominantSparseEigenAD/eig.py
DominantSparseEigenAD/symeig.py
DominantSparseEigenAD-0.0.1.dist-info/LICENSE
DominantSparseEigenAD-0.0.1.dist-info/METADATA
DominantSparseEigenAD-0.0.1.dist-info/WHEEL
DominantSparseEigenAD-0.0.1.dist-info/top_level.txt
DominantSparseEigenAD-0.0.1.dist-info/RECORD
