Metadata-Version: 2.1
Name: DominantSparseEigenAD
Version: 0.0.1
Summary: Reverse-mode AD of dominant sparse eigensolver using Pytorch.
Home-page: https://github.com/buwantaiji/DominantSparseEigenAD
Author: Hao Xie
Author-email: xiehao18@iphy.ac.cn
License: UNKNOWN
Keywords: automatic differentiation dominant eigensolver Pytorch
Platform: UNKNOWN
Classifier: Programming Language :: Python :: 3
Classifier: License :: OSI Approved :: Apache Software License
Classifier: Operating System :: OS Independent
Requires-Python: >=3
Requires-Dist: numpy
Requires-Dist: torch (>=1.3.0)
